conf.py
finstmt/__init__.py
finstmt/bs/__init__.py
finstmt/bs/config.py
finstmt/bs/main.py
finstmt/check.py
finstmt/clean/__init__.py
finstmt/clean/name.py
finstmt/combined/__init__.py
finstmt/combined/combinator.py
finstmt/combined/statements.py
finstmt/config_manage/__init__.py
finstmt/config_manage/base.py
finstmt/config_manage/data.py
finstmt/config_manage/global_.py
finstmt/config_manage/statement.py
finstmt/config_manage/statements.py
finstmt/exc.py
finstmt/findata/__init__.py
finstmt/findata/period_data.py
finstmt/findata/statement_item.py
finstmt/findata/statementsbase.py
finstmt/forecast/__init__.py
finstmt/forecast/config.py
finstmt/forecast/dataframe.py
finstmt/forecast/main.py
finstmt/forecast/models/__init__.py
finstmt/forecast/models/average.py
finstmt/forecast/models/base.py
finstmt/forecast/models/cagr.py
finstmt/forecast/models/chooser.py
finstmt/forecast/models/manual.py
finstmt/forecast/models/prophet.py
finstmt/forecast/models/recent.py
finstmt/forecast/models/trend.py
finstmt/forecast/plot.py
finstmt/forecast/statements.py
finstmt/inc/__init__.py
finstmt/inc/config.py
finstmt/inc/main.py
finstmt/items/__init__.py
finstmt/items/config.py
finstmt/loaders/__init__.py
finstmt/loaders/capiq.py
finstmt/logger.py
finstmt/resolver/__init__.py
finstmt/resolver/base.py
finstmt/resolver/forecast.py
finstmt/resolver/history.py
finstmt/resolver/solve.py
version.py
finstmt-1.4.0.dist-info/WHEEL
finstmt-1.4.0.dist-info/LICENSE.md
finstmt-1.4.0.dist-info/METADATA
finstmt-1.4.0.dist-info/RECORD
