Metadata-Version: 2.1
Name: finstmt
Version: 1.4.0
Summary: Contains classes to work with financial statement data. Can calculate free cash flows and help project financial statements.
License: MIT
Author: Nick DeRobertis
Author-email: whoopnip@gmail.com
Requires-Python: >=3.8.1,<4.0
Classifier: Development Status :: 3 - Alpha
Classifier: Intended Audience :: Developers
Classifier: License :: OSI Approved :: MIT License
Classifier: Programming Language :: Python :: 3
Classifier: Programming Language :: Python :: 3.9
Classifier: Programming Language :: Python :: 3.10
Classifier: Programming Language :: Python :: 3.11
Classifier: Programming Language :: Python :: 3.10
Classifier: Programming Language :: Python :: 3.11
Classifier: Programming Language :: Python :: 3.7
Classifier: Programming Language :: Python :: 3.8
Classifier: Programming Language :: Python :: 3.9
Provides-Extra: forecast
Requires-Dist: matplotlib
Requires-Dist: pandas
Requires-Dist: prophet ; extra == "forecast"
Requires-Dist: statsmodels
Requires-Dist: sympy
Requires-Dist: tqdm
Requires-Dist: typing-extensions (>=4.0.1)
Requires-Dist: xlrd
Project-URL: documentation, https://nickderobertis.github.io/py-finstmt
Project-URL: repository, https://github.com/nickderobertis/py-finstmt
